needle_agent/__init__.py
needle_agent/js_event_list
needle_agent/unix_cmd_list
needle_agent/libinjection2/linux/_libinjection.so
needle_agent/libinjection2/linux/libinjection.py
needle_agent/libinjection2/mac_x86_64/_libinjection.so
needle_agent/libinjection2/mac_x86_64/libinjection.py
needle_sdk/__init__.py
needle_sdk/js_event_list
needle_sdk/scanners_list
needle_sdk/unix_cmd_list
needle_sdk/core/classes.py
needle_sdk/core/needle_app.py
needle_sdk/core/utilities.py
needle_sdk/core/wrappers.py
needle_sdk/core/data/js_event
needle_sdk/core/data/scan
needle_sdk/core/data/unix_cmd
needle_sdk/core/libinjection2/linux/_libinjection.so
needle_sdk/core/libinjection2/linux/libinjection.py
needle_sdk/core/libinjection2/mac_x86_64/_libinjection.so
needle_sdk/core/libinjection2/mac_x86_64/libinjection.py
needle_sdk/libinjection2/linux/_libinjection.so
needle_sdk/libinjection2/linux/libinjection.py
needle_sdk/libinjection2/mac_x86_64/_libinjection.so
needle_sdk/libinjection2/mac_x86_64/libinjection.py
needle_sdk-1.8.2.dist-info/LICENSE
needle_sdk-1.8.2.dist-info/METADATA
needle_sdk-1.8.2.dist-info/WHEEL
needle_sdk-1.8.2.dist-info/top_level.txt
needle_sdk-1.8.2.dist-info/RECORD
