Metadata-Version: 2.1
Name: needle-sdk
Version: 1.8.2
Summary: Needle.sh SDK for Python
Home-page: https://needle.sh
Author: Needle.sh team
Author-email: hello@needle.sh
License: UNKNOWN
Platform: UNKNOWN
Classifier: Programming Language :: Python :: 3
Classifier: License :: Other/Proprietary License
Classifier: Operating System :: OS Independent
Requires-Python: >=3.0
Requires-Dist: requests
